conditions/__init__.py
conditions/conditions.py
conditions/exceptions.py
conditions/fields.py
conditions/lists.py
conditions/static/conditions/img/icon-information.png
conditions/static/conditions/img/icon-minus.png
conditions/static/conditions/img/icon-plus.png
conditions/static/conditions/js/conditions_widget.js
conditions/templates/conditions/conditions_widget.html
conditions/types.py
django_conditions-0.9.18.dist-info/LICENSE
django_conditions-0.9.18.dist-info/WHEEL
django_conditions-0.9.18.dist-info/METADATA
django_conditions-0.9.18.dist-info/RECORD
