Metadata-Version: 2.1
Name: django-conditions
Version: 0.9.18
Summary: A Django app that allows creation of conditional logic in admin.
Home-page: https://github.com/RevolutionTech/django-conditions
License: ISC
Author: Lucas Connors
Author-email: lucas@revolutiontech.ca
Requires-Python: >=3.7,<4.0
Classifier: Environment :: Web Environment
Classifier: Framework :: Django
Classifier: Framework :: Django :: 2.2
Classifier: Framework :: Django :: 3.0
Classifier: Framework :: Django :: 3.1
Classifier: Framework :: Django :: 3.2
Classifier: Intended Audience :: Developers
Classifier: License :: OSI Approved
Classifier: Operating System :: OS Independent
Classifier: Programming Language :: Python :: 3
Classifier: Programming Language :: Python :: 3.10
Classifier: Programming Language :: Python :: 3.7
Classifier: Programming Language :: Python :: 3.8
Classifier: Programming Language :: Python :: 3.9
Classifier: Topic :: Internet :: WWW/HTTP
Classifier: Topic :: Internet :: WWW/HTTP :: Dynamic Content
Requires-Dist: Django (>=2.2,<4.0a0)
Requires-Dist: django-jsonfield (>=1.1,<2.0)
Project-URL: Repository, https://github.com/RevolutionTech/django-conditions
